{
  "plugins": [
    "react",
    "import"
  ],
  "rules": {
    "react/forbid-elements": [
      "warn",
      {
        "forbid": []
      }
    ],
    "no-restricted-imports": [
      "warn",
      {
        "patterns": []
      }
    ],
    "no-restricted-syntax": [
      "warn",
      {
        "selector": "Literal[value=/#[0-9a-fA-F]{3,8}\\b/]",
        "message": "Raw hex color — use a design-system color token via var()."
      },
      {
        "selector": "Literal[value=/\\b\\d+px\\b/]",
        "message": "Raw px value — use a design-system spacing token via var()."
      },
      {
        "selector": "Literal[value=/font-family\\s*:\\s*(?!['\\\"]?(?:Aeonik|Heldane Display|Inter))/i]",
        "message": "Font not provided by the design system. Available: Aeonik, Heldane Display, Inter."
      }
    ]
  },
  "overrides": [
    {
      "files": [
        "**/index.js"
      ],
      "rules": {
        "no-restricted-imports": "off"
      }
    }
  ],
  "x-omelette": {
    "components": {},
    "tokens": [
      "--abyss",
      "--accent",
      "--anis",
      "--anis-200",
      "--anis-bg",
      "--anis-deep",
      "--anthracite-100",
      "--anthracite-400",
      "--anthracite-500",
      "--anthracite-600",
      "--anthracite-700",
      "--anthracite-800",
      "--anthracite-850",
      "--anthracite-900",
      "--bg",
      "--bg-body",
      "--bg-elev",
      "--bg-light-10",
      "--bg-light-20",
      "--bg-light-30",
      "--border",
      "--border-dark",
      "--border-light",
      "--border-light-hair",
      "--border-medium",
      "--error",
      "--error-110",
      "--fg",
      "--fg-muted",
      "--font-mono",
      "--font-sans",
      "--font-serif",
      "--granit",
      "--granit-200",
      "--granit-bg",
      "--gray-100",
      "--gray-20",
      "--gray-30",
      "--gray-40",
      "--gray-50",
      "--gray-60",
      "--gray-70",
      "--gray-80",
      "--gray-90",
      "--indigo-100",
      "--indigo-200",
      "--indigo-300",
      "--indigo-400",
      "--lagoon",
      "--lagoon-200",
      "--lagoon-bg",
      "--lilas",
      "--lilas-200",
      "--lilas-bg",
      "--lilas-deep",
      "--link",
      "--pineapple",
      "--pineapple-200",
      "--pineapple-bg",
      "--primary",
      "--primary-10",
      "--primary-100",
      "--primary-110",
      "--primary-20",
      "--primary-30",
      "--primary-40",
      "--primary-50",
      "--primary-60",
      "--primary-70",
      "--primary-80",
      "--primary-90",
      "--radius-12",
      "--radius-16",
      "--radius-20",
      "--radius-4",
      "--radius-6",
      "--radius-8",
      "--radius-pill",
      "--shadow-card-light",
      "--shadow-pop",
      "--space-1",
      "--space-10",
      "--space-2",
      "--space-3",
      "--space-4",
      "--space-5",
      "--space-6",
      "--space-7",
      "--space-8",
      "--space-9",
      "--success",
      "--success-110",
      "--text-100",
      "--text-110",
      "--text-80",
      "--text-90",
      "--viz-blue",
      "--viz-green",
      "--viz-indigo",
      "--viz-magenta",
      "--viz-orange",
      "--viz-red",
      "--viz-yellow",
      "--warning",
      "--warning-110"
    ],
    "tokenKinds": {
      "--font-sans": "font",
      "--font-serif": "font",
      "--font-mono": "font",
      "--indigo-100": "color",
      "--indigo-200": "color",
      "--indigo-300": "color",
      "--indigo-400": "color",
      "--primary-10": "color",
      "--primary-20": "color",
      "--primary-30": "color",
      "--primary-40": "color",
      "--primary-50": "color",
      "--primary-60": "color",
      "--primary-70": "color",
      "--primary-80": "color",
      "--primary-90": "color",
      "--primary-100": "color",
      "--primary-110": "color",
      "--anthracite-100": "color",
      "--anthracite-400": "color",
      "--anthracite-500": "color",
      "--anthracite-600": "color",
      "--anthracite-700": "color",
      "--anthracite-800": "color",
      "--anthracite-900": "color",
      "--anthracite-850": "color",
      "--abyss": "color",
      "--text-80": "font",
      "--text-90": "font",
      "--text-100": "font",
      "--text-110": "font",
      "--gray-20": "color",
      "--gray-30": "color",
      "--gray-40": "color",
      "--gray-50": "color",
      "--gray-60": "color",
      "--gray-70": "color",
      "--gray-80": "color",
      "--gray-90": "color",
      "--gray-100": "color",
      "--bg-body": "color",
      "--bg-light-10": "color",
      "--bg-light-20": "color",
      "--bg-light-30": "color",
      "--border-light": "color",
      "--border-medium": "color",
      "--border-dark": "color",
      "--anis": "color",
      "--anis-200": "color",
      "--anis-deep": "color",
      "--anis-bg": "color",
      "--pineapple": "color",
      "--pineapple-200": "color",
      "--pineapple-bg": "color",
      "--lilas": "color",
      "--lilas-200": "color",
      "--lilas-deep": "color",
      "--lilas-bg": "color",
      "--lagoon": "color",
      "--lagoon-200": "color",
      "--lagoon-bg": "color",
      "--granit": "color",
      "--granit-200": "color",
      "--granit-bg": "color",
      "--success": "color",
      "--success-110": "color",
      "--error": "color",
      "--error-110": "color",
      "--warning": "color",
      "--warning-110": "color",
      "--viz-red": "color",
      "--viz-orange": "color",
      "--viz-yellow": "color",
      "--viz-green": "color",
      "--viz-blue": "color",
      "--viz-indigo": "color",
      "--viz-magenta": "color",
      "--radius-4": "radius",
      "--radius-6": "radius",
      "--radius-8": "radius",
      "--radius-12": "radius",
      "--radius-16": "radius",
      "--radius-20": "radius",
      "--radius-pill": "radius",
      "--space-1": "spacing",
      "--space-2": "spacing",
      "--space-3": "spacing",
      "--space-4": "spacing",
      "--space-5": "spacing",
      "--space-6": "spacing",
      "--space-7": "spacing",
      "--space-8": "spacing",
      "--space-9": "spacing",
      "--space-10": "spacing",
      "--shadow-card-light": "shadow",
      "--shadow-pop": "shadow",
      "--border-light-hair": "color",
      "--bg": "color",
      "--bg-elev": "shadow",
      "--fg": "color",
      "--fg-muted": "color",
      "--border": "color",
      "--primary": "color",
      "--link": "color",
      "--accent": "color"
    },
    "fontFamilies": [
      "Aeonik",
      "Heldane Display",
      "Inter"
    ]
  }
}